lograder/__init__.py
lograder/random_utils.py
lograder/types.py
lograder/data/__init__.py
lograder/data/build.py
lograder/data/cxx.py
lograder/data/messages.py
lograder/data/paths.py
lograder/data/penalties.py
lograder/grader/__init__.py
lograder/grader/metadata.py
lograder/grader/submission_handler.py
lograder/grader/addons/__init__.py
lograder/grader/addons/addon.py
lograder/grader/addons/valgrind.py
lograder/grader/builders/__init__.py
lograder/grader/builders/dispatcher.py
lograder/grader/builders/cpp/__init__.py
lograder/grader/builders/cpp/cmake.py
lograder/grader/builders/cpp/cxx_source.py
lograder/grader/builders/interfaces/__init__.py
lograder/grader/builders/interfaces/builder.py
lograder/grader/builders/interfaces/cli_builder.py
lograder/grader/formatters/__init__.py
lograder/grader/formatters/dispatcher.py
lograder/grader/formatters/formatter.py
lograder/grader/json/__init__.py
lograder/grader/json/raw_gradescope.py
lograder/grader/penalties/__init__.py
lograder/grader/penalties/interfaces/__init__.py
lograder/grader/penalties/interfaces/penalty.py
lograder/grader/tests/__init__.py
lograder/grader/tests/file_test.py
lograder/grader/tests/interfaces/__init__.py
lograder/grader/tests/interfaces/cli_test.py
lograder/grader/tests/interfaces/output_test.py
lograder/grader/tests/interfaces/test.py
lograder/grader/tests/interfaces/unit_test.py
lograder/grader/tests/output_comparison/__init__.py
lograder/grader/tests/output_comparison/file.py
lograder/grader/tests/output_comparison/generator.py
lograder/grader/tests/output_comparison/output_tests.py
lograder/grader/tests/output_comparison/simple.py
lograder/grader/tests/output_comparison/template.py
lograder/grader/tests/output_comparison/types.py
lograder/grader/tests/output_comparison/validation.py
lograder/grader/tests/unit_tests/__init__.py
lograder/grader/tests/unit_tests/catch2.py
lograder/grader/tests/unit_tests/directory.py
lograder/grader/unit_testers/__init__.py
lograder/grader/unit_testers/catch2.py
lograder-0.1.7.dist-info/licenses/LICENSE
lograder-0.1.7.dist-info/METADATA
lograder-0.1.7.dist-info/WHEEL
lograder-0.1.7.dist-info/top_level.txt
lograder-0.1.7.dist-info/RECORD
