Metadata-Version: 2.4
Name: lograder
Version: 0.1.7
Summary: An API for easy Gradescope Autograder assignment creation.
Author-email: lognd <logan@logand.app>
License: Copyright 2025 Logan Dapp
Project-URL: Homepage, https://github.com/lognd/lograder
Project-URL: Documentation, https://github.com/lognd/lograder
Project-URL: Source, https://github.com/lognd/lograder
Project-URL: Issues, https://github.com/lognd/lograder/issues
Keywords: gradescope,autograder
Classifier: Programming Language :: Python :: 3
Classifier: License :: OSI Approved :: MIT License
Classifier: Operating System :: OS Independent
Requires-Python: >=3.10
License-File: LICENSE
Requires-Dist: pydantic>=2.11.7
Requires-Dist: colorama>=0.4.6
Requires-Dist: typing_extensions>=4.0.0
Provides-Extra: dev
Requires-Dist: pytest>=7.0; extra == "dev"
Requires-Dist: black>=24.0; extra == "dev"
Requires-Dist: ruff>=0.2; extra == "dev"
Requires-Dist: isort>=5.13; extra == "dev"
Requires-Dist: mypy>=1.0; extra == "dev"
Requires-Dist: pytest>=8.4.1; extra == "dev"
Requires-Dist: types-colorama>=0.4.15.20250801; extra == "dev"
Requires-Dist: pycycle>=0.0.8; extra == "dev"
Dynamic: license-file
